evals/__init__.py
evals/version.py
evals/benchmark/__init__.py
evals/benchmark/benchmark.py
evals/benchmark/utils.py
evals/benchmark/stresscli/__init__.py
evals/benchmark/stresscli/stresscli.py
evals/benchmark/stresscli/commands/__init__.py
evals/benchmark/stresscli/commands/dump.py
evals/benchmark/stresscli/commands/load_test.py
evals/benchmark/stresscli/commands/main.py
evals/benchmark/stresscli/commands/metrics.py
evals/benchmark/stresscli/commands/metrics_docker.py
evals/benchmark/stresscli/commands/metrics_util.py
evals/benchmark/stresscli/commands/report.py
evals/benchmark/stresscli/commands/utilization.py
evals/benchmark/stresscli/commands/utils.py
evals/benchmark/stresscli/commands/validate.py
evals/benchmark/stresscli/locust/__init__.py
evals/benchmark/stresscli/locust/aistress.py
evals/benchmark/stresscli/locust/audioqnabench.py
evals/benchmark/stresscli/locust/audioqnafixed.py
evals/benchmark/stresscli/locust/chatqna_qlist_pubmed.py
evals/benchmark/stresscli/locust/chatqnabench.py
evals/benchmark/stresscli/locust/chatqnafixed.py
evals/benchmark/stresscli/locust/codegenbench.py
evals/benchmark/stresscli/locust/codegenfixed.py
evals/benchmark/stresscli/locust/codetransbench.py
evals/benchmark/stresscli/locust/codetransfixed.py
evals/benchmark/stresscli/locust/constant_load_shape.py
evals/benchmark/stresscli/locust/docsumbench.py
evals/benchmark/stresscli/locust/docsumfixed.py
evals/benchmark/stresscli/locust/embeddingfixed.py
evals/benchmark/stresscli/locust/embedservefixed.py
evals/benchmark/stresscli/locust/faqgenbench.py
evals/benchmark/stresscli/locust/faqgenfixed.py
evals/benchmark/stresscli/locust/gmc_chatqnafixed.py
evals/benchmark/stresscli/locust/llmfixed.py
evals/benchmark/stresscli/locust/llmservefixed.py
evals/benchmark/stresscli/locust/locust.conf
evals/benchmark/stresscli/locust/poisson_load_shape.py
evals/benchmark/stresscli/locust/rerankingfixed.py
evals/benchmark/stresscli/locust/rerankservefixed.py
opea_eval-1.5.dist-info/licenses/LICENSE
opea_eval-1.5.dist-info/METADATA
opea_eval-1.5.dist-info/WHEEL
opea_eval-1.5.dist-info/top_level.txt
opea_eval-1.5.dist-info/RECORD
