Metadata-Version: 2.4
Name: opea-eval
Version: 1.5
Summary: Evaluation and benchmark for Generative AI
Home-page: https://github.com/opea-project/GenAIEval
Author: Intel AISE AIPC Team
Author-email: haihao.shen@intel.com, feng.tian@intel.com, chang1.wang@intel.com, kaokao.lv@intel.com
Requires-Python: >=3.10
License-File: LICENSE
Dynamic: author
Dynamic: author-email
Dynamic: description
Dynamic: description-content-type
Dynamic: home-page
Dynamic: license-file
Dynamic: requires-python
Dynamic: summary
